slycot/__config__.py
slycot/__init__.py
slycot/_wrapper.so
slycot/analysis.py
slycot/examples.py
slycot/math.py
slycot/setup.py
slycot/synthesis.py
slycot/transform.py
slycot/version.py
slycot/tests/__init__.py
slycot/tests/test.py
slycot-0.2.0.dist-info/DESCRIPTION.rst
slycot-0.2.0.dist-info/METADATA
slycot-0.2.0.dist-info/metadata.json
slycot-0.2.0.dist-info/RECORD
slycot-0.2.0.dist-info/top_level.txt
slycot-0.2.0.dist-info/WHEEL
