Metadata-Version: 2.0
Name: slycot
Version: 0.2.0
Summary: Slycot: a wrapper for the SLICOT control and systems library
Home-page: https://github.com/jgoppert/Slycot
Author: James Goppert
Author-email: james.goppert@gmail.com
License: BSD
Download-URL: https://github.com/jgoppert/Slycot
Platform: Windows
Platform: Linux
Platform: Solaris
Platform: Mac OS-X
Platform: Unix
Classifier: Development Status :: 3 - Alpha
Classifier: Intended Audience :: Science/Research
Classifier: Intended Audience :: Developers
Classifier: License :: OSI Approved
Classifier: Programming Language :: C
Classifier: Programming Language :: Python
Classifier: Programming Language :: Python :: 3
Classifier: Topic :: Software Development
Classifier: Topic :: Scientific/Engineering
Classifier: Operating System :: Microsoft :: Windows
Classifier: Operating System :: POSIX
Classifier: Operating System :: Unix
Classifier: Operating System :: MacOS
